correldata/__init__.py
correldata-1.6.0.dist-info/LICENSE
correldata-1.6.0.dist-info/WHEEL
correldata-1.6.0.dist-info/METADATA
correldata-1.6.0.dist-info/RECORD
