Metadata-Version: 2.1
Name: correldata
Version: 1.6.0
Summary: Read/write vectors of correlated data from/to a csv file.
Author-email: Mathieu Daëron <mathieu@daeron.fr>
Requires-Python: >=3.11
Classifier: License :: OSI Approved :: MIT License
Requires-Dist: numpy>=2.1.1
Requires-Dist: uncertainties>=3.2.2
Project-URL: Home, https://github.com/mdaeron/D95thermo
